Metadata-Version: 2.1
Name: dittoffi
Version: 0.0.3
Summary: Ditto FFI bindings for Python.
Author-email: Ditto Engineering Team <engineering@ditto.live>
License: Ditto Binary License
Keywords: database,P2P,CRDT,FFI
License-File: LICENSE.md
